dtensor/__init__.py
dtensor/visualize.py
dtensor/visualize_example.py
dtensor-0.0.1.dist-info/licenses/LICENSE
dtensor-0.0.1.dist-info/WHEEL
dtensor-0.0.1.dist-info/METADATA
dtensor-0.0.1.dist-info/RECORD
