Metadata-Version: 2.4
Name: dtensor
Version: 0.0.1
Summary: Facilities built around PyTorch DTensor
Author-email: Yi Wang <yi.wang.2005@gmail.com>
Requires-Python: >=3.9
Classifier: Development Status :: 3 - Alpha
Classifier: Intended Audience :: Developers
Classifier: Programming Language :: Python :: 3
Classifier: Programming Language :: Python :: 3.9
License-File: LICENSE
Requires-Dist: torch>=2.6
Requires-Dist: tabulate
Requires-Dist: types-tabulate
Requires-Dist: matplotlib
Requires-Dist: rich
Project-URL: Bug Tracker, https://github.com/wangkuiyi/dtensor/issues
Project-URL: Homepage, https://github.com/wangkuiyi/dtensor
